Metadata-Version: 2.1
Name: discordxyz
Version: 0.1.8
Summary: discordxyz
Home-page: https://github.com/AlgotJon/discordxyz
Author: Algot Jon
Author-email: Algot.dn@gmail.com
License: MIT
Platform: UNKNOWN
Requires-Python: >=3.6
